<?xml version="1.0" encoding="UTF-8"?>

<CodeSystem xmlns="http://hl7.org/fhir">
  <id value="v3-csaid"/>
  <language value="en"/>
  <text>
    <status value="generated"/>
    <div xmlns="http://www.w3.org/1999/xhtml">
                  
      <p>Nature of injury (NOI) codes, which are part of the Work Injury or Disease Information coding system (CAN/CSA-Z795-96 - R2003).</p>
                  
      <p>The CSA code set includes 3 parts: Nature of injury (NOI), body part (BP), side of body (SB).  </p>
                  
      <p>For example: </p>
                  
      <ul>
                     
        <li>
                        
          <p>NOI - Cut or laceration Injury = 03400</p>
                     
        </li>
                     
        <li>
                        
          <p>BP - Upper Arm body part = 31100</p>
                     
        </li>
                     
        <li>
                        
          <p>SOB - Left Side of Body = L</p>
                     
        </li>
                  
      </ul>
                  
      <p>The Body Part codes are qualified by the Side of Body codes code system, to be more precise in specifying the location of the injury being coded.</p>
                  
      <p>Code set is maintained by the Canadian Standards Association (CSA).</p>
                  
      <p>set is maintained by the Canadian Standards Association (CSA).</p>
                  
      <p>The Canadian Standards Association 5060 Spectrum Way Mississauga, Ontario Canada L4W 5N6</p>
                  
      <p>Phone: (416) 747-4000 1-800-463-6727 Fax: (416) 747-2473</p>
               
    </div>
  </text>
  <url value="http://terminology.hl7.org/CodeSystem/v3-csaid"/>
  <identifier>
    <system value="urn:ietf:rfc:3986"/>
    <value value="urn:oid:2.16.840.1.113883.6.235"/>
  </identifier>
  <name value="csaid"/>
  <title value="CAN/CSA-Z795-96"/>
  <status value="active"/>
  <date value="2017-07-31"/>
  <publisher value="HL7"/>
  <contact>
    <name value="Canadian Standards Association (CSA)"/>
  </contact>
  <description value=" Nature of injury (NOI) codes, which are part of the Work Injury or Disease Information coding system (CAN/CSA-Z795-96 - R2003). The CSA code set includes 3 parts: Nature of injury (NOI), body part (BP), side of body (SB). For example:   NOI - Cut or laceration Injury = 03400  BP - Upper Arm body part = 31100  SOB - Left Side of Body = L The Body Part codes are qualified by the Side of Body codes code system, to be more precise in specifying the location of the injury being coded. Code set is maintained by the Canadian Standards Association (CSA). set is maintained by the Canadian Standards Association (CSA). The Canadian Standards Association 5060 Spectrum Way Mississauga, Ontario Canada L4W 5N6 Phone: (416) 747-4000 1-800-463-6727 Fax: (416) 747-2473"/>
  <content value="fragment"/>
</CodeSystem>