<?xml version="1.0" encoding="UTF-8"?>

<CodeSystem xmlns="http://hl7.org/fhir">
  <id value="v3-ucum"/>
  <language value="en"/>
  <text>
    <status value="generated"/>
    <div xmlns="http://www.w3.org/1999/xhtml">
                  
      <p>Unified Code for Units of Measure</p>
               
    </div>
  </text>
  <extension url="http://hl7.org/fhir/StructureDefinition/codesystem-legalese">
    <valueString value="Is NOT in UMLS."/>
  </extension>
  <extension url="http://hl7.org/fhir/StructureDefinition/codesystem-contributor">
    <extension url="name">
      <valueString value="Regenstrief Institute"/>
    </extension>
    <extension url="role">
      <valueString value="Sponsor"/>
    </extension>
  </extension>
  <url value="http://terminology.hl7.org/CodeSystem/v3-ucum"/>
  <identifier>
    <system value="urn:ietf:rfc:3986"/>
    <value value="urn:oid:2.16.840.1.113883.6.8"/>
  </identifier>
  <name value="ucum"/>
  <title value="UCUM"/>
  <status value="active"/>
  <date value="2018-08-12"/>
  <publisher value="Regenstrief"/>
  <contact>
    <name value="Regenstrief Institute"/>
  </contact>
  <description value="Unified Code for Units of Measure"/>
  <content value="not-present"/>
</CodeSystem>