<?xml version="1.0" encoding="UTF-8"?>

<CodeSystem xmlns="http://hl7.org/fhir">
  <id value="v3-W1-W2"/>
  <language value="en"/>
  <text>
    <status value="generated"/>
    <div xmlns="http://www.w3.org/1999/xhtml">
                  
      <p>WHO rec# drug codes</p>
               
    </div>
  </text>
  <url value="http://terminology.hl7.org/CodeSystem/v3-W1-W2"/>
  <identifier>
    <system value="urn:ietf:rfc:3986"/>
    <value value="urn:oid:2.16.840.1.113883.6.71"/>
  </identifier>
  <name value="W1-W2"/>
  <title value="WHO rec# drug codes"/>
  <status value="active"/>
  <date value="2017-07-31"/>
  <description value=" WHO rec# drug codes"/>
  <content value="fragment"/>
</CodeSystem>