<?xml version="1.0" encoding="UTF-8"?>

<NamingSystem xmlns="http://hl7.org/fhir">
  <id value="v3-ISO3166-1retired"/>
  <name value="ISO31661retired"/>
  <title value="ISO 3166 2 Character Country Codes"/>
  <status value="retired"/>
  <kind value="codesystem"/>
  <date value="2019-03-20T00:00:00-04:00"/>
  <publisher value="ISO"/>
  <contact>
    <name value="International Standards Organization (ISO)"/>
  </contact>
  <responsible value="ISO"/>
  <description value="Two character country codes Note that this OID was erroneously entered into HL7 some years ago, and has recently been replaced by 1.0.3166.1 at the request of ISO."/>
  <uniqueId>
    <type value="oid"/>
    <value value="2.16.1"/>
    <preferred value="true"/>
  </uniqueId>
  <uniqueId>
    <type value="uri"/>
    <value value="http://terminology.hl7.org/CodeSystem/v3-ISO3166-1retired"/>
    <preferred value="true"/>
  </uniqueId>
</NamingSystem>